{
  "json_language": "en",
  "country_code": "AU",
  "country_name": "Australia",
  "city_name": "Casino",
  "language": [
    "English"
  ],
  "lat": -28.8667,
  "lon": 153.05,
  "currencies": {
    "AUD": {
      "symbol": "$",
      "name": "Australian dollar"
    }
  },
  "population": 9968,
  "welcome_message_title": "Welcome to Casino",
  "welcome_message_body": "\"Welcome to Casino, Australia! Known for its quaint charm and agricultural roots, we invite you to immerse yourself in our vibrant community and discover all that our city has to offer.\"",
  "welcome_message_image": null,
  "avg_prices": {
    "city": "casino",
    "currency": "usd",
    "avg_price_index": 19.718947368421055,
    "prices": {
      "meal": 16.77,
      "meal_for_two": 40.24,
      "fast_food": 10.06,
      "beer": 4.69,
      "imported_beer": 5.36,
      "coffee": 3.35,
      "soda": 2.01,
      "water_small": 2.68,
      "bus_ticket": 3.35,
      "monthly_pass": 107.3,
      "taxi_start": 3.02,
      "taxi_km": 0.67,
      "taxi_waiting": 33.26,
      "gasoline": 1.32,
      "mobile_tariff": 0.15,
      "internet": 60.36,
      "fitness": 45.09,
      "tennis": 24.59,
      "cinema": 10.39
    }
  },
  "emergency_numbers": {
    "general": "112"
  },
  "restaurants": null,
  "airports": [
    {
      "airport_name": "Casino",
      "iata_code": "CSI",
      "icao_code": "YCAS",
      "distance_km": 2.0,
      "gmt": "10",
      "country": "Australia",
      "timezone": "Australia/Sydney",
      "terminals": [
        {
          "name": "Terminal 1",
          "description": "The main terminal at Casino Airport, serving domestic and international flights."
        },
        {
          "name": "Terminal 2",
          "description": "A smaller terminal at Casino Airport, primarily used for regional flights."
        }
      ],
      "website": "https://www.casinoairport.com.au/",
      "wifi": {
        "available": true,
        "network_name": "Casino Airport WiFi",
        "note": "Free WiFi is available throughout the airport."
      }
    },
    {
      "airport_name": "Lismore",
      "iata_code": "LSY",
      "icao_code": "YLIS",
      "distance_km": 21.0,
      "gmt": "10",
      "country": "Australia",
      "timezone": "Australia/Sydney",
      "terminals": [
        {
          "name": "Main Terminal",
          "description": "The main terminal at Lismore Airport handles all domestic and international flights."
        }
      ],
      "website": "https://lismoreairport.com.au/",
      "wifi": {
        "available": true,
        "network_name": "Lismore Airport WiFi",
        "note": "Free WiFi is available throughout the terminal."
      }
    },
    {
      "airport_name": "Evans Head",
      "iata_code": "EVH",
      "icao_code": "YEVD",
      "distance_km": 44.1,
      "gmt": "10",
      "country": "Australia",
      "timezone": "Australia/Sydney",
      "terminals": [
        {
          "name": "Main Terminal",
          "description": "The main terminal at Evans Head Airport serves both domestic and international flights."
        }
      ],
      "website": "https://www.evansheadairport.com.au/",
      "wifi": {
        "available": true,
        "network_name": "EVH Airport WiFi",
        "note": "Free WiFi is available throughout the terminal building."
      }
    },
    {
      "airport_name": "Ballina Byron Gateway",
      "iata_code": "BNK",
      "icao_code": "YBNA",
      "distance_km": 49.4,
      "gmt": "10",
      "country": "Australia",
      "timezone": "Australia/Sydney",
      "terminals": [
        {
          "name": "Main Terminal",
          "description": "The main terminal at Ballina Byron Gateway Airport serves both domestic and international flights."
        }
      ],
      "website": "https://www.ballinabyronairport.com.au/",
      "wifi": {
        "available": true,
        "network_name": "Ballina Airport WiFi",
        "note": "Free WiFi is available throughout the terminal."
      }
    }
  ],
  "_meta": {
    "generated_at": "2025-08-04T19:27:53.529502Z",
    "env": "development",
    "source": "justarrived-generator"
  }
}