{
  "json_language": "en",
  "country_code": "BR",
  "country_name": "Brazil",
  "city_name": "Gloria",
  "language": [
    "Portuguese"
  ],
  "lat": -9.3389,
  "lon": -38.2569,
  "currencies": {
    "BRL": {
      "symbol": "R$",
      "name": "Brazilian real"
    }
  },
  "population": 15524,
  "welcome_message_title": "Welcome to Gloria",
  "welcome_message_body": "\"Welcome to the charming city of Gloria, Brazil! Known for its breathtaking landscapes and vibrant culture, we invite you to explore and indulge in all that our beautiful city has to offer.\"",
  "avg_prices": {
    "city": "gloria",
    "currency": "usd",
    "avg_price_index": 5.905263157894737,
    "prices": {
      "meal": 2.39,
      "meal_for_two": 15.33,
      "fast_food": 2.21,
      "beer": 1.24,
      "imported_beer": 2.12,
      "coffee": 2.12,
      "soda": 0.88,
      "water_small": 0.35,
      "bus_ticket": 0.22,
      "monthly_pass": 12.38,
      "taxi_start": 0.97,
      "taxi_km": 0.71,
      "taxi_waiting": 1.77,
      "gasoline": 1.28,
      "mobile_tariff": 0.17,
      "internet": 22.98,
      "fitness": 30.94,
      "tennis": 8.84,
      "cinema": 5.3
    }
  },
  "emergency_numbers": {
    "general": "112",
    "ambulance": "192",
    "fire": "193"
  },
  "_meta": {
    "generated_at": "2025-08-03T10:30:54.017727Z",
    "env": "development",
    "source": "justarrived-generator"
  }
}