{
  "json_language": "en",
  "country_code": "BR",
  "country_name": "Brazil",
  "city_name": "Garibaldi",
  "language": [
    "Portuguese"
  ],
  "lat": -29.2558,
  "lon": -51.5339,
  "currencies": {
    "BRL": {
      "symbol": "R$",
      "name": "Brazilian real"
    }
  },
  "population": 34335,
  "welcome_message_title": "Welcome to Garibaldi",
  "welcome_message_body": "\"Welcome to Garibaldi! Known for its charming atmosphere and famous for its wine production, we invite you to immerse yourself in the beauty of our city and experience all it has to offer. Enjoy your stay and discover the wonders of Garibaldi!\"",
  "welcome_message_image": null,
  "avg_prices": {
    "city": "garibaldi",
    "currency": "usd",
    "avg_price_index": 10.07684210526316,
    "prices": {
      "meal": 5.59,
      "meal_for_two": 22.36,
      "fast_food": 7.45,
      "beer": 0.93,
      "imported_beer": 2.8,
      "coffee": 1.27,
      "soda": 0.84,
      "water_small": 0.61,
      "bus_ticket": 1.04,
      "monthly_pass": 39.13,
      "taxi_start": 1.86,
      "taxi_km": 0.56,
      "taxi_waiting": 4.47,
      "gasoline": 1.25,
      "mobile_tariff": 0.06,
      "internet": 15.84,
      "fitness": 19.25,
      "tennis": 60.56,
      "cinema": 5.59
    }
  },
  "emergency_numbers": {
    "general": "112",
    "ambulance": "192",
    "fire": "193"
  },
  "_meta": {
    "generated_at": "2025-08-04T00:35:34.056057Z",
    "env": "development",
    "source": "justarrived-generator"
  }
}