{
  "json_language": "en",
  "country_code": "BR",
  "country_name": "Brazil",
  "city_name": "Manacapuru",
  "language": [
    "Portuguese"
  ],
  "lat": -3.2997,
  "lon": -60.6206,
  "currencies": {
    "BRL": {
      "symbol": "R$",
      "name": "Brazilian real"
    }
  },
  "population": 98502,
  "welcome_message_title": "Welcome to Manacapuru",
  "welcome_message_body": "Welcome to Manacapuru, a charming city known for its beautiful Amazonian landscapes and vibrant culture. We hope you enjoy your time here and take the opportunity to explore all that this unique destination has to offer.",
  "welcome_message_image": null,
  "avg_prices": {
    "city": "manacapuru",
    "currency": "usd",
    "avg_price_index": 7.98578947368421,
    "prices": {
      "meal": 3.53,
      "meal_for_two": 22.36,
      "fast_food": 5.59,
      "beer": 1.3,
      "imported_beer": 3.35,
      "coffee": 1.56,
      "soda": 0.84,
      "water_small": 0.45,
      "bus_ticket": 0.71,
      "monthly_pass": 46.58,
      "taxi_start": 0.95,
      "taxi_km": 0.65,
      "taxi_waiting": 6.52,
      "gasoline": 1.27,
      "mobile_tariff": 0.26,
      "internet": 19.52,
      "fitness": 16.26,
      "tennis": 14.44,
      "cinema": 5.59
    }
  },
  "emergency_numbers": {
    "general": "112",
    "ambulance": "192",
    "fire": "193"
  },
  "restaurants": null,
  "airports": null,
  "_meta": {
    "generated_at": "2025-08-04T18:19:43.084796Z",
    "env": "development",
    "source": "justarrived-generator"
  }
}