{
  "json_language": "en",
  "country_code": "CG",
  "country_name": "Congo (Brazzaville)",
  "city_name": "Brazzaville",
  "language": [
    "French"
  ],
  "lat": -4.2667,
  "lon": 15.2667,
  "currencies": {
    "XAF": {
      "symbol": "Fr",
      "name": "Central African CFA franc"
    }
  },
  "population": 2557100,
  "welcome_message_title": "Welcome to Brazzaville",
  "welcome_message_body": "Welcome to Brazzaville, the vibrant capital of Congo! Get ready to be enchanted by the city's unique blend of French colonial architecture, lively markets, and beautiful riverfront. We invite you to explore and immerse yourself in all that Brazzaville has to offer. Enjoy your stay!",
  "welcome_message_image": "https://images.unsplash.com/photo-1633960722151-bc0ab5ba9003?crop=entropy&cs=tinysrgb&fit=max&fm=jpg&ixid=M3w3ODcwNDh8MHwxfHNlYXJjaHwxfHxCcmF6emF2aWxsZXxlbnwwfHx8fDE3NTQyNjI0Nzh8MA&ixlib=rb-4.1.0&q=80&w=1080",
  "avg_prices": {
    "city": "brazzaville",
    "currency": "usd",
    "avg_price_index": 21.22157894736842,
    "prices": {
      "meal": 7.84,
      "meal_for_two": 64.25,
      "fast_food": 10.51,
      "beer": 2.2,
      "imported_beer": 1.5,
      "coffee": 3.93,
      "soda": 1.95,
      "water_small": 1.42,
      "bus_ticket": 0.59,
      "monthly_pass": 31.78,
      "taxi_start": 1.67,
      "taxi_km": 1.67,
      "taxi_waiting": 8.0,
      "gasoline": 0.33,
      "mobile_tariff": 0.1,
      "internet": 192.23,
      "fitness": 40.05,
      "tennis": 28.35,
      "cinema": 4.84
    }
  },
  "emergency_numbers": {
    "general": "112"
  },
  "restaurants": [
    {
      "name": "Royal Spice",
      "type": "Indian Restaurant",
      "description": "Royal Spice is a indian restaurant located in Brazzaville.",
      "address": "Brazzaville",
      "tel": null,
      "location": {
        "lat": -4.270325010495567,
        "lon": 15.269610841568305
      }
    },
    {
      "name": "Jardin Des Saveurs",
      "type": "French Restaurant",
      "description": "Jardin Des Saveurs is a french restaurant located in Brazzaville.",
      "address": "Brazzaville",
      "tel": null,
      "location": {
        "lat": -4.269488508510862,
        "lon": 15.268919290862875
      }
    },
    {
      "name": "Mikhael's Hotel Restaurant",
      "type": "Restaurant",
      "description": "Mikhael's Hotel Restaurant is a restaurant located in Brazzaville.",
      "address": "Brazzaville",
      "tel": null,
      "location": {
        "lat": -4.270799637656263,
        "lon": 15.281178099541455
      }
    },
    {
      "name": "Mami Wata",
      "type": "Restaurant",
      "description": "Mami Wata is a restaurant located in Brazzaville.",
      "address": "Avenue de la Corniche, Brazzaville",
      "tel": "05 534 2879",
      "location": {
        "lat": -4.277618444511268,
        "lon": 15.28372544606228
      }
    },
    {
      "name": "La Mandarine",
      "type": "Café",
      "description": "La Mandarine is a café located in Brazzaville.",
      "address": "Avenue Foch, Brazzaville",
      "tel": "06 666 6600",
      "location": {
        "lat": -4.2776907081255535,
        "lon": 15.278191513619964
      }
    }
  ],
  "_meta": {
    "generated_at": "2025-08-04T11:31:58.999741Z",
    "env": "development",
    "source": "justarrived-generator"
  }
}