{
  "json_language": "en",
  "country_code": "FR",
  "country_name": "France",
  "city_name": "Montrouge",
  "language": [
    "French"
  ],
  "lat": 48.8172,
  "lon": 2.3219,
  "currencies": {
    "EUR": {
      "symbol": "€",
      "name": "Euro"
    }
  },
  "population": 46273,
  "welcome_message_title": "Welcome to Montrouge",
  "welcome_message_body": "\"Welcome to Montrouge, known for its charming streets and vibrant culture. We invite you to explore and indulge in all the delights our city has to offer. Enjoy your stay!\"",
  "welcome_message_image": null,
  "avg_prices": {
    "city": "montrouge",
    "currency": "usd",
    "avg_price_index": 17.95421052631579,
    "prices": {
      "meal": 15.58,
      "meal_for_two": 62.32,
      "fast_food": 10.39,
      "beer": 7.27,
      "imported_beer": 6.23,
      "coffee": 3.8,
      "soda": 2.84,
      "water_small": 2.4,
      "bus_ticket": 1.97,
      "monthly_pass": 77.9,
      "taxi_start": 5.19,
      "taxi_km": 1.9,
      "taxi_waiting": 47.26,
      "gasoline": 2.1,
      "mobile_tariff": 0.17,
      "internet": 30.52,
      "fitness": 37.16,
      "tennis": 13.67,
      "cinema": 12.46
    }
  },
  "emergency_numbers": {
    "general": "112",
    "ambulance": "15",
    "fire": "18",
    "police": "17"
  },
  "restaurants": null,
  "_meta": {
    "generated_at": "2025-08-04T11:57:08.046732Z",
    "env": "development",
    "source": "justarrived-generator"
  }
}