{
  "json_language": "en",
  "country_code": "GB",
  "country_name": "United Kingdom",
  "city_name": "Great Wyrley",
  "language": [
    "English"
  ],
  "lat": 52.6593,
  "lon": -2.0102,
  "currencies": {
    "GBP": {
      "symbol": "£",
      "name": "British pound"
    }
  },
  "population": 10954,
  "welcome_message_title": "Welcome to Great Wyrley",
  "welcome_message_body": "\"Welcome to Great Wyrley, a charming town with a rich history and friendly locals. We invite you to explore its quaint streets, taste the delicious local cuisine, and immerse yourself in its unique culture. Enjoy your stay!\"",
  "welcome_message_image": null,
  "avg_prices": {
    "city": "great wyrley",
    "currency": "usd",
    "avg_price_index": 15.57842105263158,
    "prices": {
      "meal": 15.62,
      "meal_for_two": 60.06,
      "fast_food": 6.59,
      "beer": 4.2,
      "imported_beer": 4.8,
      "coffee": 3.2,
      "soda": 2.2,
      "water_small": 1.16,
      "bus_ticket": 2.88,
      "monthly_pass": 81.98,
      "taxi_start": 3.0,
      "taxi_km": 1.49,
      "taxi_waiting": 18.02,
      "gasoline": 1.89,
      "mobile_tariff": 0.06,
      "internet": 39.64,
      "fitness": 24.82,
      "tennis": 10.57,
      "cinema": 13.81
    }
  },
  "emergency_numbers": {
    "general": "112"
  },
  "restaurants": null,
  "_meta": {
    "generated_at": "2025-08-04T12:56:54.769164Z",
    "env": "development",
    "source": "justarrived-generator"
  }
}