{
  "json_language": "en",
  "country_code": "GB",
  "country_name": "United Kingdom",
  "city_name": "Willenhall",
  "language": [
    "English"
  ],
  "lat": 52.5798,
  "lon": -2.0605,
  "currencies": {
    "GBP": {
      "symbol": "£",
      "name": "British pound"
    }
  },
  "population": 51429,
  "welcome_message_title": "Welcome to Willenhall",
  "welcome_message_body": "\"Welcome to Willenhall, a charming town known for its rich history and friendly locals. We invite you to explore and enjoy our quaint streets, local shops, and vibrant culture during your stay. We hope you have a wonderful time here!\"",
  "welcome_message_image": null,
  "avg_prices": {
    "city": "willenhall",
    "currency": "usd",
    "avg_price_index": 18.380000000000003,
    "prices": {
      "meal": 14.41,
      "meal_for_two": 63.06,
      "fast_food": 7.21,
      "beer": 3.0,
      "imported_beer": 4.8,
      "coffee": 4.2,
      "soda": 1.47,
      "water_small": 1.2,
      "bus_ticket": 3.3,
      "monthly_pass": 115.29,
      "taxi_start": 3.48,
      "taxi_km": 1.19,
      "taxi_waiting": 14.41,
      "gasoline": 1.85,
      "mobile_tariff": 0.06,
      "internet": 46.13,
      "fitness": 30.03,
      "tennis": 20.02,
      "cinema": 14.11
    }
  },
  "emergency_numbers": {
    "general": "112"
  },
  "restaurants": null,
  "_meta": {
    "generated_at": "2025-08-04T11:54:56.926837Z",
    "env": "development",
    "source": "justarrived-generator"
  }
}