{
  "json_language": "en",
  "country_code": "IL",
  "country_name": "Israel",
  "city_name": "Eilat",
  "language": [
    "Arabic"
  ],
  "lat": 29.55,
  "lon": 34.95,
  "currencies": {
    "ILS": {
      "symbol": "₪",
      "name": "Israeli new shekel"
    }
  },
  "population": 51935,
  "welcome_message_title": "Welcome to Eilat",
  "welcome_message_body": "\"Welcome to Eilat, a charming city known for its stunning beaches and vibrant nightlife. Get ready to explore and bask in the beauty of this seaside paradise!\"",
  "welcome_message_image": null,
  "avg_prices": {
    "city": "eilat",
    "currency": "usd",
    "avg_price_index": 15.79736842105263,
    "prices": {
      "meal": 23.3,
      "meal_for_two": 49.38,
      "fast_food": 18.35,
      "beer": 7.57,
      "imported_beer": 7.57,
      "coffee": 3.32,
      "soda": 2.91,
      "water_small": 2.33,
      "bus_ticket": 1.43,
      "monthly_pass": 32.63,
      "taxi_start": 6.55,
      "taxi_km": 1.46,
      "taxi_waiting": 16.02,
      "gasoline": 2.01,
      "mobile_tariff": 0.06,
      "internet": 26.22,
      "fitness": 58.26,
      "tennis": 29.13,
      "cinema": 11.65
    }
  },
  "emergency_numbers": {
    "ambulance": "101",
    "fire": "102",
    "police": "100"
  },
  "restaurants": null,
  "_meta": {
    "generated_at": "2025-08-04T11:54:43.742178Z",
    "env": "development",
    "source": "justarrived-generator"
  }
}