{
  "json_language": "en",
  "country_code": "IT",
  "country_name": "Italy",
  "city_name": "Arona",
  "language": [
    "Italian"
  ],
  "lat": 45.7569,
  "lon": 8.56,
  "currencies": {
    "EUR": {
      "symbol": "€",
      "name": "Euro"
    }
  },
  "population": 13694,
  "welcome_message_title": "Welcome to Arona",
  "welcome_message_body": "Welcome to Arona, Italy! Get ready to experience the charming city known for its picturesque views of Lake Maggiore. We invite you to discover all that Arona has to offer and make unforgettable memories. Enjoy your stay!",
  "welcome_message_image": null,
  "avg_prices": {
    "city": "arona",
    "currency": "usd",
    "avg_price_index": 10.984736842105264,
    "prices": {
      "meal": 9.35,
      "meal_for_two": 41.55,
      "fast_food": 8.31,
      "beer": 1.82,
      "imported_beer": 3.12,
      "coffee": 1.73,
      "soda": 1.35,
      "water_small": 0.97,
      "bus_ticket": 1.19,
      "monthly_pass": 22.85,
      "taxi_start": 3.51,
      "taxi_km": 1.82,
      "taxi_waiting": 20.57,
      "gasoline": 1.63,
      "mobile_tariff": 0.26,
      "internet": 31.81,
      "fitness": 32.46,
      "tennis": 18.7,
      "cinema": 5.71
    }
  },
  "emergency_numbers": {
    "general": "112",
    "ambulance": "118",
    "fire": "115",
    "police": "113"
  },
  "restaurants": null,
  "airports": [
    {
      "airport_name": "Milano Malpensa",
      "iata_code": "MXP",
      "icao_code": "LIMC",
      "distance_km": 18.6,
      "gmt": "1",
      "country": "Italy",
      "timezone": "Europe/Rome",
      "terminals": [],
      "website": "",
      "wifi": {}
    },
    {
      "airport_name": "Lugano",
      "iata_code": "LUG",
      "icao_code": "LSZA",
      "distance_km": 42.7,
      "gmt": "1",
      "country": "Switzerland",
      "timezone": "Europe/Zurich",
      "terminals": [],
      "website": "",
      "wifi": {}
    }
  ],
  "_meta": {
    "generated_at": "2025-08-04T20:22:27.036297Z",
    "env": "development",
    "source": "justarrived-generator"
  }
}