{
  "json_language": "en",
  "country_code": "IT",
  "country_name": "Italy",
  "city_name": "Novi Ligure",
  "lat": 44.7592,
  "lon": 8.7856,
  "population": 27252,
  "welcome_message_title": "Welcome to Novi Ligure",
  "avg_prices": {
    "city": "novi ligure",
    "currency": "usd",
    "avg_price_index": 13.07842105263158,
    "prices": {
      "meal": 17.14,
      "meal_for_two": 46.74,
      "fast_food": 8.57,
      "beer": 4.15,
      "imported_beer": 4.67,
      "coffee": 1.53,
      "soda": 2.08,
      "water_small": 1.37,
      "bus_ticket": 1.56,
      "monthly_pass": 36.35,
      "taxi_start": 5.19,
      "taxi_km": 1.19,
      "taxi_waiting": 25.97,
      "gasoline": 2.07,
      "mobile_tariff": 0.05,
      "internet": 28.16,
      "fitness": 36.25,
      "tennis": 15.06,
      "cinema": 10.39
    }
  },
  "_meta": {
    "generated_at": "2025-08-01T18:33:32.658869Z",
    "env": "development",
    "source": "justarrived-generator"
  }
}