{
  "json_language": "en",
  "country_code": "KZ",
  "country_name": "Kazakhstan",
  "city_name": "Beyneu",
  "language": [
    "Kazakh"
  ],
  "lat": 45.3247,
  "lon": 55.1958,
  "currencies": {
    "KZT": {
      "symbol": "₸",
      "name": "Kazakhstani tenge"
    }
  },
  "population": 40344,
  "welcome_message_title": "Welcome to Beyneu",
  "welcome_message_body": "Welcome to Beyneu, Kazakhstan! Get ready to be charmed by our city's unique blend of traditional culture and modern development. Enjoy exploring our bustling streets and experiencing all that Beyneu has to offer.",
  "welcome_message_image": null,
  "avg_prices": {
    "city": "beyneu",
    "currency": "usd",
    "avg_price_index": 7.003157894736842,
    "prices": {
      "meal": 4.74,
      "meal_for_two": 16.84,
      "fast_food": 3.79,
      "beer": 1.37,
      "imported_beer": 1.05,
      "coffee": 1.72,
      "soda": 0.91,
      "water_small": 0.26,
      "bus_ticket": 0.28,
      "monthly_pass": 10.95,
      "taxi_start": 1.26,
      "taxi_km": 0.32,
      "taxi_waiting": 4.21,
      "gasoline": 0.42,
      "mobile_tariff": 0.02,
      "internet": 10.18,
      "fitness": 63.16,
      "tennis": 7.37,
      "cinema": 4.21
    }
  },
  "emergency_numbers": {
    "general": "112",
    "ambulance": "103",
    "fire": "101",
    "police": "102"
  },
  "restaurants": null,
  "_meta": {
    "generated_at": "2025-08-04T12:00:21.585170Z",
    "env": "development",
    "source": "justarrived-generator"
  }
}