{
  "json_language": "en",
  "country_code": "MA",
  "country_name": "Morocco",
  "city_name": "Ounagha",
  "language": [
    "Arabic"
  ],
  "lat": 31.5333,
  "lon": -9.55,
  "currencies": {
    "MAD": {
      "symbol": "د.م.",
      "name": "Moroccan dirham"
    }
  },
  "population": 13310,
  "welcome_message_title": "Welcome to Ounagha",
  "welcome_message_body": "\"Welcome to Ounagha, Morocco! Known for its beautiful architecture and warm hospitality, we invite you to soak in the charm of our city and discover its rich history. Enjoy your stay and immerse yourself in all that Ounagha has to offer.\"",
  "welcome_message_image": null,
  "avg_prices": {
    "city": "ounagha",
    "currency": "usd",
    "avg_price_index": 6.757894736842106,
    "prices": {
      "meal": 2.56,
      "meal_for_two": 24.53,
      "fast_food": 4.19,
      "beer": 4.08,
      "imported_beer": 3.93,
      "coffee": 1.5,
      "soda": 0.58,
      "water_small": 0.36,
      "bus_ticket": 0.37,
      "monthly_pass": 13.49,
      "taxi_start": 0.65,
      "taxi_km": 0.65,
      "taxi_waiting": 3.26,
      "gasoline": 1.19,
      "mobile_tariff": 0.08,
      "internet": 24.19,
      "fitness": 18.61,
      "tennis": 17.83,
      "cinema": 6.35
    }
  },
  "emergency_numbers": {
    "ambulance": "15",
    "fire": "15",
    "police": "19"
  },
  "restaurants": null,
  "airports": [
    {
      "airport_name": "Essaouira",
      "iata_code": "ESU",
      "icao_code": "GMMI",
      "distance_km": 19.6,
      "gmt": null,
      "country": "Morocco",
      "timezone": "Africa/Casablanca",
      "terminals": [
        {
          "name": "Terminal 1",
          "description": "The main terminal at Essaouira Airport, serving both domestic and international flights."
        },
        {
          "name": "Terminal 2",
          "description": "A smaller terminal used for private and charter flights."
        }
      ],
      "website": "https://www.essaouira-airport.com/",
      "wifi": {
        "available": true,
        "network_name": "ESSAOUIRA-AIRPORT-WIFI",
        "note": "Free WiFi is available throughout the airport."
      }
    }
  ],
  "_meta": {
    "generated_at": "2025-08-04T20:22:34.903376Z",
    "env": "development",
    "source": "justarrived-generator"
  }
}