{
  "json_language": "en",
  "country_code": "PG",
  "country_name": "Papua New Guinea",
  "city_name": "Tari",
  "language": [
    "English"
  ],
  "lat": -5.8489,
  "lon": 142.9506,
  "currencies": {
    "PGK": {
      "symbol": "K",
      "name": "Papua New Guinean kina"
    }
  },
  "population": 15413,
  "welcome_message_title": "Welcome to Tari",
  "welcome_message_body": "Welcome to Tari, a charming city nestled in the highlands of Papua New Guinea. Known for its vibrant cultural traditions and stunning natural landscapes, we invite you to explore and immerse yourself in all that Tari has to offer. Enjoy your stay!",
  "welcome_message_image": null,
  "avg_prices": {
    "city": "tari",
    "currency": "usd",
    "avg_price_index": 41.933684210526316,
    "prices": {
      "meal": 14.2,
      "meal_for_two": 38.33,
      "fast_food": 7.81,
      "beer": 4.26,
      "imported_beer": 5.68,
      "coffee": 2.27,
      "soda": 1.28,
      "water_small": 0.85,
      "bus_ticket": 0.57,
      "monthly_pass": 38.27,
      "taxi_start": 5.68,
      "taxi_km": 1.7,
      "taxi_waiting": 14.2,
      "gasoline": 1.21,
      "mobile_tariff": 0.28,
      "internet": 567.87,
      "fitness": 60.34,
      "tennis": 22.71,
      "cinema": 9.23
    }
  },
  "emergency_numbers": {
    "fire": "110",
    "police": "000"
  },
  "restaurants": null,
  "_meta": {
    "generated_at": "2025-08-04T12:36:52.090646Z",
    "env": "development",
    "source": "justarrived-generator"
  }
}