{
  "json_language": "en",
  "country_code": "PL",
  "country_name": "Poland",
  "city_name": "Grudziadz",
  "language": [
    "Polish"
  ],
  "lat": 53.4875,
  "lon": 18.755,
  "currencies": {
    "PLN": {
      "symbol": "zł",
      "name": "Polish złoty"
    }
  },
  "population": 90890,
  "welcome_message_title": "Welcome to Grudziadz",
  "welcome_message_body": "Welcome to Grudziadz, a charming city known for its beautiful medieval architecture and rich history. We invite you to explore and enjoy all that our city has to offer during your visit.",
  "welcome_message_image": null,
  "avg_prices": {
    "city": "grudziadz",
    "currency": "usd",
    "avg_price_index": 7.106315789473685,
    "prices": {
      "meal": 5.55,
      "meal_for_two": 33.32,
      "fast_food": 3.33,
      "beer": 2.22,
      "imported_beer": 1.78,
      "coffee": 2.22,
      "soda": 1.11,
      "water_small": 0.89,
      "bus_ticket": 0.76,
      "monthly_pass": 13.33,
      "taxi_start": 1.78,
      "taxi_km": 0.41,
      "taxi_waiting": 10.66,
      "gasoline": 1.36,
      "mobile_tariff": 0.09,
      "internet": 8.89,
      "fitness": 26.66,
      "tennis": 15.55,
      "cinema": 5.11
    }
  },
  "emergency_numbers": {
    "general": "112",
    "ambulance": "999",
    "fire": "998",
    "police": "997"
  },
  "_meta": {
    "generated_at": "2025-08-04T00:30:20.453111Z",
    "env": "development",
    "source": "justarrived-generator"
  }
}