{
  "json_language": "en",
  "country_code": "SE",
  "country_name": "Sweden",
  "city_name": "Lidingo",
  "language": [
    "Swedish"
  ],
  "lat": 59.363,
  "lon": 18.151,
  "currencies": {
    "SEK": {
      "symbol": "kr",
      "name": "Swedish krona"
    }
  },
  "population": 48377,
  "welcome_message_title": "Welcome to Lidingo",
  "welcome_message_body": "Welcome to Lidingo, Sweden! Prepare to be enchanted by the city's stunning natural beauty and quaint charm. We invite you to discover all that Lidingo has to offer and make unforgettable memories.",
  "welcome_message_image": null,
  "avg_prices": {
    "city": "lidingo",
    "currency": "usd",
    "avg_price_index": 20.892105263157895,
    "prices": {
      "meal": 12.38,
      "meal_for_two": 76.21,
      "fast_food": 8.57,
      "beer": 6.67,
      "imported_beer": 6.67,
      "coffee": 3.87,
      "soda": 2.28,
      "water_small": 2.05,
      "bus_ticket": 3.72,
      "monthly_pass": 92.4,
      "taxi_start": 4.76,
      "taxi_km": 2.71,
      "taxi_waiting": 49.77,
      "gasoline": 2.13,
      "mobile_tariff": 0.14,
      "internet": 33.5,
      "fitness": 41.25,
      "tennis": 33.58,
      "cinema": 14.29
    }
  },
  "emergency_numbers": {
    "general": "112"
  },
  "_meta": {
    "generated_at": "2025-08-04T00:33:20.767404Z",
    "env": "development",
    "source": "justarrived-generator"
  }
}