{
  "json_language": "en",
  "country_code": "TT",
  "country_name": "Trinidad and Tobago",
  "city_name": "Princes Town",
  "language": [
    "English"
  ],
  "lat": 10.2667,
  "lon": -61.3833,
  "currencies": {
    "TTD": {
      "symbol": "$",
      "name": "Trinidad and Tobago dollar"
    }
  },
  "population": 28335,
  "welcome_message_title": "Welcome to Princes Town",
  "welcome_message_body": "\"Welcome to Princes Town, where the vibrant culture and warm hospitality of Trinidad and Tobago await you. Get ready to discover our charming town known for its rich history and delicious cuisine – we invite you to immerse yourself in the beauty and charm of Princes Town.\"",
  "welcome_message_image": null,
  "avg_prices": {
    "city": "princes town",
    "currency": "usd",
    "avg_price_index": 14.14421052631579,
    "prices": {
      "meal": 7.36,
      "meal_for_two": 73.62,
      "fast_food": 6.63,
      "beer": 1.47,
      "imported_beer": 2.58,
      "coffee": 3.02,
      "soda": 0.96,
      "water_small": 0.74,
      "bus_ticket": 1.47,
      "monthly_pass": 38.09,
      "taxi_start": 0.81,
      "taxi_km": 0.74,
      "taxi_waiting": 14.72,
      "gasoline": 0.82,
      "mobile_tariff": 0.29,
      "internet": 49.17,
      "fitness": 40.49,
      "tennis": 18.4,
      "cinema": 7.36
    }
  },
  "emergency_numbers": {
    "ambulance": "990",
    "fire": "990",
    "police": "999"
  },
  "restaurants": null,
  "airports": [
    {
      "airport_name": "Piarco International",
      "iata_code": "POS",
      "icao_code": "TTPP",
      "distance_km": 37.6,
      "gmt": "-4",
      "country": "Trinidad and Tobago",
      "timezone": "America/Port_of_Spain",
      "terminals": [
        {
          "name": "Terminal 1",
          "description": "The main terminal at Piarco International Airport, serving both international and domestic flights."
        },
        {
          "name": "Terminal 2",
          "description": "A secondary terminal at Piarco International Airport, primarily used for regional and domestic flights."
        }
      ],
      "website": "https://www.piarcoairport.com/",
      "wifi": {
        "available": true,
        "network_name": "Piarco Airport WiFi",
        "note": "Complimentary WiFi is available throughout the airport."
      }
    }
  ],
  "_meta": {
    "generated_at": "2025-08-04T18:43:45.728162Z",
    "env": "development",
    "source": "justarrived-generator"
  }
}