{
  "json_language": "en",
  "country_code": "US",
  "country_name": "United States",
  "city_name": "Batavia",
  "language": [
    "English"
  ],
  "lat": 42.9987,
  "lon": -78.1802,
  "currencies": {
    "USD": {
      "symbol": "$",
      "name": "United States dollar"
    }
  },
  "population": 15494,
  "welcome_message_title": "Welcome to Batavia",
  "welcome_message_body": "\"Welcome to Batavia, a charming city known for its rich history and picturesque landscapes. We invite you to explore and enjoy all that our beautiful city has to offer. Have a wonderful stay!\"",
  "welcome_message_image": null,
  "avg_prices": {
    "city": "batavia",
    "currency": "usd",
    "avg_price_index": 17.832631578947368,
    "prices": {
      "meal": 15.0,
      "meal_for_two": 80.0,
      "fast_food": 8.0,
      "beer": 3.5,
      "imported_beer": 5.5,
      "coffee": 3.88,
      "soda": 2.0,
      "water_small": 1.67,
      "bus_ticket": 2.5,
      "monthly_pass": 85.0,
      "taxi_start": 2.5,
      "taxi_km": 1.09,
      "taxi_waiting": 30.0,
      "gasoline": 1.18,
      "mobile_tariff": 0.25,
      "internet": 68.75,
      "fitness": 10.0,
      "tennis": 8.0,
      "cinema": 10.0
    }
  },
  "emergency_numbers": {
    "general": "112"
  },
  "restaurants": null,
  "airports": [
    {
      "airport_name": "Dupage County",
      "iata_code": "DPA",
      "icao_code": "KDPA",
      "distance_km": 9.1,
      "gmt": "-6",
      "country": "United States",
      "timezone": "America/Chicago",
      "terminals": [
        {
          "name": "Main Terminal",
          "description": "The main terminal at Dupage County Airport serves domestic and international flights."
        },
        {
          "name": "Private Terminal",
          "description": "The private terminal at Dupage County Airport caters to private and charter flights."
        }
      ],
      "website": "https://www.dupageairport.com/",
      "wifi": {
        "available": true,
        "network_name": "DPA Airport WiFi",
        "note": "Passengers can connect to the airport's free WiFi network for up to 2 hours."
      }
    },
    {
      "airport_name": "Municipal Airport",
      "iata_code": "AUZ",
      "icao_code": "KARR",
      "distance_km": 10.9,
      "gmt": "-6",
      "country": "United States",
      "timezone": "America/Chicago",
      "terminals": [
        {
          "name": "Terminal 1",
          "description": "The main terminal for domestic flights."
        },
        {
          "name": "Terminal 2",
          "description": "The smaller terminal for regional flights."
        }
      ],
      "website": "https://www.municipalairport.com/",
      "wifi": {
        "available": true,
        "network_name": "Municipal Airport WiFi",
        "note": "Free WiFi is available throughout the airport."
      }
    },
    {
      "airport_name": "Lewis Lockport",
      "iata_code": "LOT",
      "icao_code": "KLOT",
      "distance_km": 36.5,
      "gmt": "-6",
      "country": "United States",
      "timezone": "America/Chicago",
      "terminals": [
        {
          "name": "Main Terminal",
          "description": "The main terminal at Lewis Lockport Airport handles all commercial flights and is equipped with modern amenities for travelers."
        },
        {
          "name": "Private Terminal",
          "description": "The private terminal at Lewis Lockport Airport caters to private and chartered flights, offering a luxurious and exclusive experience for passengers."
        }
      ],
      "website": "https://www.lewislockportairport.com",
      "wifi": {
        "available": true,
        "network_name": "LLA_WiFi",
        "note": "Passengers can enjoy free WiFi throughout the airport."
      }
    },
    {
      "airport_name": "Chicago O'hare International",
      "iata_code": "ORD",
      "icao_code": "KORD",
      "distance_km": 36.5,
      "gmt": "-6",
      "country": "United States",
      "timezone": "America/Chicago",
      "terminals": [
        {
          "name": "Terminal 1",
          "description": "The largest terminal at O'hare International Airport, serving major domestic and international airlines."
        },
        {
          "name": "Terminal 2",
          "description": "A smaller terminal at O'hare International Airport, serving primarily domestic airlines."
        },
        {
          "name": "Terminal 3",
          "description": "The second largest terminal at O'hare International Airport, serving major domestic and international airlines."
        },
        {
          "name": "Terminal 5",
          "description": "The international terminal at O'hare International Airport, serving a variety of international airlines."
        }
      ],
      "website": "https://www.flychicago.com/ohare/home/pages/default.aspx",
      "wifi": {
        "available": true,
        "network_name": "ORD-WiFi",
        "note": "Free WiFi is available throughout the airport, but may require a brief registration process."
      }
    },
    {
      "airport_name": "Municipal",
      "iata_code": "JOT",
      "icao_code": "KJOT",
      "distance_km": 39.8,
      "gmt": "-6",
      "country": "United States",
      "timezone": "America/Chicago",
      "terminals": [
        {
          "name": "Main Terminal",
          "description": "The main terminal at Municipal Airport serves domestic and international flights."
        },
        {
          "name": "Cargo Terminal",
          "description": "The cargo terminal handles all freight and cargo operations at Municipal Airport."
        }
      ],
      "website": "https://www.municipalairport.com/",
      "wifi": {
        "available": true,
        "network_name": "MunicipalAirportWiFi",
        "note": "Passengers can connect to the airport's free WiFi network for internet access."
      }
    },
    {
      "airport_name": "Pal-Waukee",
      "iata_code": "PWK",
      "icao_code": "KPWK",
      "distance_km": 45.0,
      "gmt": "-6",
      "country": "United States",
      "timezone": "America/Chicago",
      "terminals": [
        {
          "name": "Main Terminal",
          "description": "The main terminal at Pal-Waukee Airport serves both domestic and international flights."
        },
        {
          "name": "Cargo Terminal",
          "description": "The cargo terminal at Pal-Waukee Airport handles all freight and cargo operations."
        }
      ],
      "website": "https://www.palwaukeeairport.com/",
      "wifi": {
        "available": true,
        "network_name": "PWK Airport WiFi",
        "note": "Complimentary WiFi is available throughout the airport."
      }
    },
    {
      "airport_name": "Midway",
      "iata_code": "MDW",
      "icao_code": "KMDW",
      "distance_km": 47.7,
      "gmt": "-6",
      "country": "United States",
      "timezone": "America/Chicago",
      "terminals": [
        {
          "name": "Terminal 1",
          "description": "This terminal serves domestic and international flights operated by Southwest Airlines."
        },
        {
          "name": "Terminal 2",
          "description": "This terminal serves domestic flights operated by Delta Air Lines."
        },
        {
          "name": "Terminal 3",
          "description": "This terminal serves domestic and international flights operated by United Airlines."
        }
      ],
      "website": "https://www.flychicago.com/midway/home/pages/default.aspx",
      "wifi": {
        "available": true,
        "network_name": "MDW Airport WiFi",
        "note": "Free WiFi is available throughout the airport."
      }
    }
  ],
  "_meta": {
    "generated_at": "2025-08-04T20:19:33.961598Z",
    "env": "development",
    "source": "justarrived-generator"
  }
}