{
  "json_language": "en",
  "country_code": "US",
  "country_name": "United States",
  "city_name": "Evesham",
  "language": [
    "English"
  ],
  "lat": 39.8605,
  "lon": -74.8947,
  "currencies": {
    "USD": {
      "symbol": "$",
      "name": "United States dollar"
    }
  },
  "population": 47612,
  "welcome_message_title": "Welcome to Evesham",
  "welcome_message_body": "\"Welcome to Evesham, a charming city known for its picturesque landscapes and rich history. We invite you to explore and enjoy our beautiful town, filled with unique attractions and friendly locals.\"",
  "welcome_message_image": null,
  "avg_prices": {
    "city": "evesham",
    "currency": "usd",
    "avg_price_index": 16.981052631578947,
    "prices": {
      "meal": 15.0,
      "meal_for_two": 50.0,
      "fast_food": 8.0,
      "beer": 6.0,
      "imported_beer": 7.0,
      "coffee": 3.83,
      "soda": 3.25,
      "water_small": 1.5,
      "bus_ticket": 2.0,
      "monthly_pass": 25.0,
      "taxi_start": 2.8,
      "taxi_km": 3.11,
      "taxi_waiting": 20.0,
      "gasoline": 1.42,
      "mobile_tariff": 0.1,
      "internet": 96.8,
      "fitness": 43.33,
      "tennis": 21.0,
      "cinema": 12.5
    }
  },
  "emergency_numbers": {
    "general": "112"
  },
  "restaurants": null,
  "airports": [
    {
      "airport_name": "North Philadelphia",
      "iata_code": "PNE",
      "icao_code": "KPNE",
      "distance_km": 26.4,
      "gmt": "-5",
      "country": "United States",
      "timezone": "America/New_York",
      "terminals": [
        {
          "name": "Terminal A",
          "description": "This terminal serves domestic flights and has a variety of amenities including restaurants, shops, and lounges."
        },
        {
          "name": "Terminal B",
          "description": "This terminal serves international flights and offers duty-free shopping and a business lounge for travelers."
        }
      ],
      "website": "https://www.phl.org/",
      "wifi": {
        "available": true,
        "network_name": "PNE Airport WiFi",
        "note": "Free WiFi is available throughout the airport. Simply connect to the network and accept the terms and conditions to access."
      }
    },
    {
      "airport_name": "Philadelphia International",
      "iata_code": "PHL",
      "icao_code": "KPHL",
      "distance_km": 29.8,
      "gmt": "-5",
      "country": "United States",
      "timezone": "America/New_York",
      "terminals": [
        {
          "name": "Terminal A",
          "description": "This terminal primarily serves domestic flights for various airlines."
        },
        {
          "name": "Terminal B",
          "description": "This terminal serves both domestic and international flights for various airlines."
        },
        {
          "name": "Terminal C",
          "description": "This terminal serves domestic and international flights for American Airlines."
        },
        {
          "name": "Terminal D",
          "description": "This terminal serves primarily international flights for various airlines."
        },
        {
          "name": "Terminal E",
          "description": "This terminal serves domestic and international flights for various airlines."
        }
      ],
      "website": "https://www.phl.org/",
      "wifi": {
        "available": true,
        "network_name": "PHL Free WiFi",
        "note": "Free WiFi is available throughout the airport. No password is required."
      }
    },
    {
      "airport_name": "Willow Grove NAS",
      "iata_code": "NXX",
      "icao_code": "KNXX",
      "distance_km": 42.9,
      "gmt": "-5",
      "country": "United States",
      "timezone": "America/New_York",
      "terminals": [
        {
          "name": "Main Terminal",
          "description": "The main terminal at Willow Grove NAS Airport."
        },
        {
          "name": "Cargo Terminal",
          "description": "The cargo terminal at Willow Grove NAS Airport."
        }
      ],
      "website": "https://www.willowgrovenasairport.com",
      "wifi": {
        "available": true,
        "network_name": "WillowGroveWiFi",
        "note": "Free WiFi is available throughout the airport."
      }
    },
    {
      "airport_name": "Wings Field",
      "iata_code": "BBX",
      "icao_code": "KLOM",
      "distance_km": 44.2,
      "gmt": "-5",
      "country": "United States",
      "timezone": "America/New_York",
      "terminals": [
        {
          "name": "Main Terminal",
          "description": "The main terminal at Wings Field Airport offers a variety of amenities for travelers, including restaurants, shops, and rental car services."
        },
        {
          "name": "Private Aviation Terminal",
          "description": "The private aviation terminal at Wings Field Airport provides a luxurious and convenient experience for private jet travelers."
        }
      ],
      "website": "https://www.wingsfieldairport.com/",
      "wifi": {
        "available": true,
        "network_name": "WingsFieldWiFi",
        "note": "Free WiFi is available throughout the airport."
      }
    },
    {
      "airport_name": "Trenton Mercer Airport",
      "iata_code": "TTN",
      "icao_code": "KTTN",
      "distance_km": 47.0,
      "gmt": "-5",
      "country": "United States",
      "timezone": "America/New_York",
      "terminals": [
        {
          "name": "Main Terminal",
          "description": "The main terminal at Trenton Mercer Airport serves all domestic flights."
        }
      ],
      "website": "https://www.mercercounty.org/departments/transportation-and-infrastructure/trenton-mercer-airport",
      "wifi": {
        "available": true,
        "network_name": "TTN Airport Wifi",
        "note": "Free wifi is available throughout the airport."
      }
    }
  ],
  "_meta": {
    "generated_at": "2025-08-04T18:30:51.372427Z",
    "env": "development",
    "source": "justarrived-generator"
  }
}