{
  "json_language": "en",
  "country_code": "US",
  "country_name": "United States",
  "city_name": "Lamont",
  "language": [
    "English"
  ],
  "lat": 35.2659,
  "lon": -118.9159,
  "currencies": {
    "USD": {
      "symbol": "$",
      "name": "United States dollar"
    }
  },
  "population": 13481,
  "welcome_message_title": "Welcome to Lamont",
  "welcome_message_body": "\"Welcome to Lamont, a charming city known for its historic landmarks and friendly locals. We invite you to explore and experience all the beauty and culture our city has to offer. Enjoy your stay!\"",
  "welcome_message_image": null,
  "avg_prices": {
    "city": "lamont",
    "currency": "usd",
    "avg_price_index": 16.59894736842105,
    "prices": {
      "meal": 16.0,
      "meal_for_two": 55.0,
      "fast_food": 9.0,
      "beer": 6.0,
      "imported_beer": 7.0,
      "coffee": 5.6,
      "soda": 2.45,
      "water_small": 2.21,
      "bus_ticket": 1.75,
      "monthly_pass": 31.0,
      "taxi_start": 3.0,
      "taxi_km": 1.71,
      "taxi_waiting": 27.0,
      "gasoline": 1.56,
      "mobile_tariff": 0.1,
      "internet": 74.0,
      "fitness": 35.0,
      "tennis": 25.0,
      "cinema": 12.0
    }
  },
  "emergency_numbers": {
    "general": "112"
  },
  "restaurants": null,
  "airports": [
    {
      "airport_name": "Meadows Field",
      "iata_code": "BFL",
      "icao_code": "KBFL",
      "distance_km": 21.7,
      "gmt": "-8",
      "country": "United States",
      "timezone": "America/Los_Angeles",
      "terminals": [
        {
          "name": "Main Terminal",
          "description": "This terminal serves all domestic and international flights."
        },
        {
          "name": "Cargo Terminal",
          "description": "This terminal handles all cargo shipments."
        }
      ],
      "website": "https://www.meadowsfieldairport.com/",
      "wifi": {
        "available": true,
        "network_name": "MBJ Airport WiFi",
        "note": "Free WiFi is available throughout the airport."
      }
    },
    {
      "airport_name": "Kern County",
      "iata_code": "TSP",
      "icao_code": "KTSP",
      "distance_km": 45.4,
      "gmt": "-8",
      "country": "United States",
      "timezone": "America/Los_Angeles",
      "terminals": [],
      "website": "",
      "wifi": {}
    }
  ],
  "_meta": {
    "generated_at": "2025-08-04T20:22:31.228922Z",
    "env": "development",
    "source": "justarrived-generator"
  }
}