{
  "json_language": "en",
  "country_code": "US",
  "country_name": "United States",
  "city_name": "Tulsa",
  "language": [
    "English"
  ],
  "lat": 36.1283,
  "lon": -95.9042,
  "currencies": {
    "USD": {
      "symbol": "$",
      "name": "United States dollar"
    }
  },
  "population": 740620,
  "welcome_message_title": "Welcome to Tulsa",
  "welcome_message_body": "Welcome to Tulsa! Get ready to experience the charm and hospitality of this vibrant city, known for its rich history, thriving arts scene, and beautiful outdoor spaces. We invite you to explore and enjoy all that Tulsa has to offer during your visit.",
  "welcome_message_image": "https://images.unsplash.com/photo-1474573892045-721452c3d98c?crop=entropy&cs=tinysrgb&fit=max&fm=jpg&ixid=M3w3ODcwNTJ8MHwxfHNlYXJjaHwxfHxUdWxzYXxlbnwwfHx8fDE3NTQyNjY2OTV8MA&ixlib=rb-4.1.0&q=80&w=1080",
  "avg_prices": {
    "city": "tulsa",
    "currency": "usd",
    "avg_price_index": 15.557894736842107,
    "prices": {
      "meal": 13.25,
      "meal_for_two": 48.0,
      "fast_food": 8.0,
      "beer": 4.0,
      "imported_beer": 5.0,
      "coffee": 4.5,
      "soda": 1.89,
      "water_small": 1.5,
      "bus_ticket": 2.5,
      "monthly_pass": 40.0,
      "taxi_start": 5.0,
      "taxi_km": 1.55,
      "taxi_waiting": 30.0,
      "gasoline": 1.02,
      "mobile_tariff": 0.33,
      "internet": 66.22,
      "fitness": 29.17,
      "tennis": 21.67,
      "cinema": 12.0
    }
  },
  "emergency_numbers": {
    "general": "112"
  },
  "restaurants": [
    {
      "name": "Cracker Barrel",
      "type": "American Restaurant",
      "description": "Cracker Barrel is a american restaurant located in Tulsa.",
      "address": "8008 E 31st St, Tulsa, OK 74145",
      "tel": "(918) 610-0414",
      "location": {
        "lat": 36.11828027951469,
        "lon": -95.88799695376152
      }
    },
    {
      "name": "Panera Bread",
      "type": "Bakery",
      "description": "Panera Bread is a bakery located in Tulsa.",
      "address": "5601 E 41st St (S Hudson St), Tulsa, OK 74135",
      "tel": "(918) 663-1600",
      "location": {
        "lat": 36.1046846,
        "lon": -95.9137804
      }
    },
    {
      "name": "Whataburger",
      "type": "Burger Joint",
      "description": "Whataburger is a burger joint located in Tulsa.",
      "address": "7568 S Olympia Ave W, Tulsa, OK 74132",
      "tel": "(918) 445-7143",
      "location": {
        "lat": 36.11437491023668,
        "lon": -95.90358442518861
      }
    },
    {
      "name": "Jumbos Hamburger",
      "type": "Burger Joint",
      "description": "Jumbos Hamburger is a burger joint located in Tulsa.",
      "address": "6558 E 41st St, Tulsa, OK 74145",
      "tel": "(918) 663-0944",
      "location": {
        "lat": 36.103852266833705,
        "lon": -95.90221791035155
      }
    },
    {
      "name": "Pho Da Cao",
      "type": "Asian Restaurant",
      "description": "Pho Da Cao is a asian restaurant located in Tulsa.",
      "address": "9066 E 31st St, Tulsa, OK 74145",
      "tel": "(918) 270-2715",
      "location": {
        "lat": 36.11860198837667,
        "lon": -95.87306449535116
      }
    }
  ],
  "airports": [
    {
      "airport_name": "R.Lloyd Jones",
      "iata_code": "RVS",
      "icao_code": "KRVS",
      "distance_km": 6.1,
      "gmt": "-6",
      "country": "United States",
      "timezone": "America/Chicago",
      "terminals": [
        {
          "name": "Main Terminal",
          "description": "The main terminal at R.Lloyd Jones Airport serves all domestic and international flights."
        },
        {
          "name": "Cargo Terminal",
          "description": "The cargo terminal at R.Lloyd Jones Airport handles all cargo and freight operations."
        }
      ],
      "website": "https://www.rljairport.com/",
      "wifi": {
        "available": true,
        "network_name": "RLJ Airport WiFi",
        "note": "Free WiFi is available throughout the airport."
      }
    },
    {
      "airport_name": "Tulsa International",
      "iata_code": "TUL",
      "icao_code": "KTUL",
      "distance_km": 7.0,
      "gmt": "-6",
      "country": "United States",
      "timezone": "America/Chicago",
      "terminals": [
        {
          "name": "Main Terminal",
          "description": "The main terminal at Tulsa International Airport serves all domestic and international flights."
        },
        {
          "name": "Concourse A",
          "description": "Concourse A at Tulsa International Airport serves primarily domestic flights."
        },
        {
          "name": "Concourse B",
          "description": "Concourse B at Tulsa International Airport serves primarily international flights."
        }
      ],
      "website": "https://www.tulsaairports.com/tulsa-international-airport/",
      "wifi": {
        "available": true,
        "network_name": "TUL Free WiFi",
        "note": "WiFi is available throughout the airport and is free for all passengers."
      }
    }
  ],
  "_meta": {
    "generated_at": "2025-08-04T18:05:03.026099Z",
    "env": "development",
    "source": "justarrived-generator"
  }
}