{
  "json_language": "en",
  "country_code": "US",
  "country_name": "United States",
  "city_name": "West Caldwell",
  "language": [
    "English"
  ],
  "lat": 40.8488,
  "lon": -74.2971,
  "currencies": {
    "USD": {
      "symbol": "$",
      "name": "United States dollar"
    }
  },
  "population": 10897,
  "welcome_message_title": "Welcome to West Caldwell",
  "welcome_message_body": "\"Welcome to West Caldwell, a charming town known for its beautiful natural landscapes and friendly community. We invite you to explore and enjoy all that our city has to offer during your stay!\"",
  "welcome_message_image": null,
  "avg_prices": {
    "city": "west caldwell",
    "currency": "usd",
    "avg_price_index": 17.010526315789473,
    "prices": {
      "meal": 20.0,
      "meal_for_two": 65.0,
      "fast_food": 8.0,
      "beer": 5.0,
      "imported_beer": 7.0,
      "coffee": 4.0,
      "soda": 2.73,
      "water_small": 1.5,
      "bus_ticket": 1.6,
      "monthly_pass": 35.0,
      "taxi_start": 3.0,
      "taxi_km": 1.24,
      "taxi_waiting": 30.0,
      "gasoline": 1.13,
      "mobile_tariff": 0.5,
      "internet": 57.5,
      "fitness": 45.0,
      "tennis": 25.0,
      "cinema": 10.0
    }
  },
  "emergency_numbers": {
    "general": "112"
  },
  "restaurants": null,
  "airports": [
    {
      "airport_name": "Caldwell Wright",
      "iata_code": "CDW",
      "icao_code": "KCDW",
      "distance_km": 3.1,
      "gmt": "-5",
      "country": "United States",
      "timezone": "America/New_York",
      "terminals": [
        {
          "name": "Main Terminal",
          "description": "The main terminal at Caldwell Wright Airport serves all commercial and private flights."
        },
        {
          "name": "Private Terminal",
          "description": "The private terminal at Caldwell Wright Airport is exclusively for private and chartered flights."
        }
      ],
      "website": "https://www.caldwellwrightairport.com/",
      "wifi": {
        "available": true,
        "network_name": "CDW Airport WiFi",
        "note": "Free WiFi is available throughout the airport."
      }
    },
    {
      "airport_name": "Municipal",
      "iata_code": "MMU",
      "icao_code": "KMMU",
      "distance_km": 11.4,
      "gmt": "-5",
      "country": "United States",
      "timezone": "America/New_York",
      "terminals": [
        {
          "name": "Main Terminal",
          "description": "The main terminal at Municipal Airport handles all domestic and international flights."
        },
        {
          "name": "Cargo Terminal",
          "description": "The cargo terminal at Municipal Airport is used for shipping and receiving of goods and materials."
        }
      ],
      "website": "https://www.municipalairport.com",
      "wifi": {
        "available": true,
        "network_name": "Municipal Airport WiFi",
        "note": "Free WiFi is available throughout the airport."
      }
    },
    {
      "airport_name": "Teterboro",
      "iata_code": "TEB",
      "icao_code": "KTEB",
      "distance_km": 19.8,
      "gmt": "-5",
      "country": "United States",
      "timezone": "America/New_York",
      "terminals": [],
      "website": "",
      "wifi": {}
    },
    {
      "airport_name": "Newark Liberty International",
      "iata_code": "EWR",
      "icao_code": "KEWR",
      "distance_km": 20.4,
      "gmt": "-5",
      "country": "United States",
      "timezone": "America/New_York",
      "terminals": [
        {
          "name": "Terminal A",
          "description": "Serves domestic and international flights."
        },
        {
          "name": "Terminal B",
          "description": "Serves domestic and international flights."
        },
        {
          "name": "Terminal C",
          "description": "Serves domestic and international flights."
        }
      ],
      "website": "https://www.newarkairport.com/",
      "wifi": {
        "available": true,
        "network_name": "EWR Free WiFi",
        "note": "Free WiFi is available throughout the airport."
      }
    },
    {
      "airport_name": "Linden",
      "iata_code": "LDJ",
      "icao_code": "KLDJ",
      "distance_km": 26.1,
      "gmt": "-5",
      "country": "United States",
      "timezone": "America/New_York",
      "terminals": [
        {
          "name": "Main Terminal",
          "description": "The main terminal at Linden Airport serves both commercial and private flights. It offers a variety of amenities for travelers."
        },
        {
          "name": "Private Terminal",
          "description": "The private terminal at Linden Airport caters to private and charter flights. It provides a luxurious and exclusive experience for travelers."
        }
      ],
      "website": "https://www.lindenairport.com/",
      "wifi": {
        "available": true,
        "network_name": "Linden Airport Wifi",
        "note": "Wifi access is free for all travelers."
      }
    },
    {
      "airport_name": "LaGuardia",
      "iata_code": "LGA",
      "icao_code": "KLGA",
      "distance_km": 36.8,
      "gmt": "-5",
      "country": "United States",
      "timezone": "America/New_York",
      "terminals": [
        {
          "name": "Terminal A",
          "description": "This terminal primarily serves domestic flights, with a few international flights to Canada."
        },
        {
          "name": "Terminal B",
          "description": "This terminal is the largest at LaGuardia and serves both domestic and international flights."
        },
        {
          "name": "Terminal C",
          "description": "This terminal serves mostly domestic flights, with a few international flights to Canada and the Caribbean."
        },
        {
          "name": "Terminal D",
          "description": "This terminal is the smallest at LaGuardia and serves only domestic flights."
        }
      ],
      "website": "https://www.laguardiaairport.com/",
      "wifi": {
        "available": true,
        "network_name": "LGA Free Wi-Fi",
        "note": "Passengers can connect for free for up to 30 minutes, after which a fee is required."
      }
    },
    {
      "airport_name": "John F Kennedy International",
      "iata_code": "JFK",
      "icao_code": "KJFK",
      "distance_km": 48.6,
      "gmt": "-5",
      "country": "United States",
      "timezone": "America/New_York",
      "terminals": [
        {
          "name": "Terminal 1",
          "description": "This terminal primarily serves international flights for various airlines."
        },
        {
          "name": "Terminal 2",
          "description": "This terminal primarily serves Delta Air Lines and its partner airlines."
        },
        {
          "name": "Terminal 4",
          "description": "This terminal serves a mix of domestic and international flights for various airlines."
        },
        {
          "name": "Terminal 5",
          "description": "This terminal serves JetBlue Airways and its partner airlines."
        },
        {
          "name": "Terminal 7",
          "description": "This terminal primarily serves British Airways and its partner airlines."
        },
        {
          "name": "Terminal 8",
          "description": "This terminal primarily serves American Airlines and its partner airlines."
        }
      ],
      "website": "https://www.jfkairport.com/",
      "wifi": {
        "available": true,
        "network_name": "JFK Airport Wi-Fi",
        "note": "Free Wi-Fi is available throughout the airport."
      }
    }
  ],
  "_meta": {
    "generated_at": "2025-08-04T20:27:30.209471Z",
    "env": "development",
    "source": "justarrived-generator"
  }
}