{
  "json_language": "en",
  "country_code": "UZ",
  "country_name": "Uzbekistan",
  "city_name": "Oltiariq",
  "language": [
    "Russian"
  ],
  "lat": 40.3917,
  "lon": 71.4767,
  "currencies": {
    "UZS": {
      "symbol": "so'm",
      "name": "Uzbekistani soʻm"
    }
  },
  "population": 25543,
  "welcome_message_title": "Welcome to Oltiariq",
  "welcome_message_body": "\"Welcome to Oltiariq, a charming city known for its rich history and vibrant culture. We invite you to explore and enjoy all that our city has to offer - from delicious cuisine to stunning architecture.\"",
  "welcome_message_image": null,
  "avg_prices": {
    "city": "oltiariq",
    "currency": "usd",
    "avg_price_index": 4.3852631578947365,
    "prices": {
      "meal": 1.75,
      "meal_for_two": 25.0,
      "fast_food": 3.0,
      "beer": 0.7,
      "imported_beer": 1.5,
      "coffee": 0.9,
      "soda": 0.36,
      "water_small": 0.4,
      "bus_ticket": 0.1,
      "monthly_pass": 10.0,
      "taxi_start": 0.37,
      "taxi_km": 0.1,
      "taxi_waiting": 1.0,
      "gasoline": 0.5,
      "mobile_tariff": 0.02,
      "internet": 18.72,
      "fitness": 12.5,
      "tennis": 5.0,
      "cinema": 1.4
    }
  },
  "emergency_numbers": {
    "general": "112"
  },
  "restaurants": null,
  "airports": [
    {
      "airport_name": "Fergana",
      "iata_code": "FEG",
      "icao_code": "UTKF",
      "distance_km": 22.2,
      "gmt": "5",
      "country": "Uzbekistan",
      "timezone": "Asia/Tashkent",
      "terminals": [],
      "website": "",
      "wifi": {}
    }
  ],
  "_meta": {
    "generated_at": "2025-08-04T20:11:30.666433Z",
    "env": "development",
    "source": "justarrived-generator"
  }
}