{
  "json_language": "en",
  "country_code": "ZA",
  "country_name": "South Africa",
  "city_name": "Krugersdorp",
  "language": [
    "Afrikaans"
  ],
  "lat": -26.1,
  "lon": 27.7667,
  "currencies": {
    "ZAR": {
      "symbol": "R",
      "name": "South African rand"
    }
  },
  "population": 140643,
  "welcome_message_title": "Welcome to Krugersdorp",
  "welcome_message_body": "Welcome to Krugersdorp, where old-world charm meets modern excitement! Explore our historic mining town, nestled in the beautiful Cradle of Humankind, and enjoy the natural beauty and unique experiences this vibrant city has to offer.",
  "welcome_message_image": null,
  "avg_prices": {
    "city": "krugersdorp",
    "currency": "usd",
    "avg_price_index": 10.17421052631579,
    "prices": {
      "meal": 8.2,
      "meal_for_two": 35.13,
      "fast_food": 4.1,
      "beer": 1.76,
      "imported_beer": 2.34,
      "coffee": 1.66,
      "soda": 0.89,
      "water_small": 0.86,
      "bus_ticket": 2.63,
      "monthly_pass": 23.42,
      "taxi_start": 1.23,
      "taxi_km": 0.76,
      "taxi_waiting": 3.81,
      "gasoline": 1.24,
      "mobile_tariff": 0.09,
      "internet": 49.77,
      "fitness": 40.01,
      "tennis": 10.73,
      "cinema": 4.68
    }
  },
  "emergency_numbers": {
    "ambulance": "10177",
    "fire": "10177",
    "police": "10111"
  },
  "restaurants": [
    {
      "name": "The Diner",
      "type": "Diner",
      "description": "The Diner is a diner located in Krugersdorp.",
      "address": "244 Voortrekker Road (Van Oordt Street), Krugersdorp, 1739",
      "tel": "011 954 0444",
      "location": {
        "lat": -26.10074384898251,
        "lon": 27.79656388803304
      }
    },
    {
      "name": "Wimpy",
      "type": "Burger Joint",
      "description": "Wimpy is a burger joint located in Krugersdorp.",
      "address": "Pretoria Street (Market Street), Krugersdorp, 1739",
      "tel": "021 665 4313",
      "location": {
        "lat": -26.097912132280637,
        "lon": 27.77665615081787
      }
    },
    {
      "name": "Ocean Basket",
      "type": "Seafood Restaurant",
      "description": "Ocean Basket is a seafood restaurant located in Krugersdorp.",
      "address": "Key West Shopping Centre, Krugersdorp",
      "tel": "011 273 1722",
      "location": {
        "lat": -26.088829587922316,
        "lon": 27.78024676730003
      }
    },
    {
      "name": "The Verandah Bistro",
      "type": "Restaurant",
      "description": "The Verandah Bistro is a restaurant located in Krugersdorp.",
      "address": "4 Shannon Road, Krugersdorp",
      "tel": "011 955 6201",
      "location": {
        "lat": -26.109301,
        "lon": 27.805839
      }
    },
    {
      "name": "Nando's",
      "type": "Portuguese Restaurant",
      "description": "Nando's is a portuguese restaurant located in Krugers dorp.",
      "address": "Key west shopping centre, Krugers dorp",
      "tel": null,
      "location": {
        "lat": -26.092816519961012,
        "lon": 27.749497952603036
      }
    }
  ],
  "_meta": {
    "generated_at": "2025-08-04T11:40:54.940799Z",
    "env": "development",
    "source": "justarrived-generator"
  }
}